setup.py
StickShift.egg-info/PKG-INFO
StickShift.egg-info/SOURCES.txt
StickShift.egg-info/dependency_links.txt
StickShift.egg-info/entry_points.txt
StickShift.egg-info/requires.txt
StickShift.egg-info/top_level.txt
stickshift/__init__.py
stickshift/__main__.py
stickshift/cli.py
stickshift/cli_strings.py
stickshift/cmd_alter.py
stickshift/cmd_clear.py
stickshift/cmd_db.py
stickshift/cmd_new.py
stickshift/cmd_setup.py
stickshift/database_manager.py
stickshift/migration_repository.py
stickshift/shell.py