Metadata-Version: 1.0
Name: StickShift
Version: 0.1.3
Summary: Database migration tool using raw sql files
Home-page: https://www.github.com/rohan-panchal/StickShift
Author: Rohan Panchal
Author-email: rohan@rohanpanchal.com
License: UNKNOWN
Platform: UNKNOWN
